SwifTCR/__init__.py
SwifTCR/cluster.py
SwifTCR/output.py
SwifTCR/preprocess.py
SwifTCR/random_data.py
SwifTCR/spark.py
SwifTCR-0.4.12.dist-info/LICENSE
SwifTCR-0.4.12.dist-info/METADATA
SwifTCR-0.4.12.dist-info/WHEEL
SwifTCR-0.4.12.dist-info/top_level.txt
SwifTCR-0.4.12.dist-info/RECORD
