Metadata-Version: 2.1
Name: SwifTCR
Version: 0.4.12
Summary: Cluster and construct netwotk graph of highly similar sequences
Author: ido
Author-email: idoh@systemsbiomed.org
Keywords: cluster,TCR,edit,distance
License-File: LICENSE
Requires-Dist: findspark
Requires-Dist: pyspark
Requires-Dist: scipy
Requires-Dist: numpy
Requires-Dist: pandas
Requires-Dist: networkx
Requires-Dist: more-itertools
